pysports/__init__.py
pysports/credentials.py
pysports/cricapi.py
pysports-1.0.2.dist-info/License
pysports-1.0.2.dist-info/METADATA
pysports-1.0.2.dist-info/WHEEL
pysports-1.0.2.dist-info/top_level.txt
pysports-1.0.2.dist-info/RECORD
